iclouder/__init__.py
iclouder/cmdline.py
iclouder/commands.py
iclouder/replacer.py
iclouder/utils.py
iclouder-0.0.2.dist-info/DESCRIPTION.rst
iclouder-0.0.2.dist-info/METADATA
iclouder-0.0.2.dist-info/RECORD
iclouder-0.0.2.dist-info/WHEEL
iclouder-0.0.2.dist-info/entry_points.txt
iclouder-0.0.2.dist-info/metadata.json
iclouder-0.0.2.dist-info/top_level.txt
