Metadata-Version: 2.0
Name: iclouder
Version: 0.0.2
Summary: upload markdown document local             image and replace path automatically
Home-page: https://github.com/free-free/mdimguploader
Author: infinite.ft
Author-email: infinite.ft@gmail.com
License: MIT
Keywords: markdown
Platform: UNKNOWN
Classifier: Intended Audience :: Developers
Classifier: License :: OSI Approved :: MIT License
Classifier: Environment :: Console
Classifier: Programming Language :: Python
Classifier: Programming Language :: Python :: 3
Classifier: Programming Language :: Python :: 3.4
Classifier: Programming Language :: Python :: 3.5
Classifier: Programming Language :: Python :: 3.6
Classifier: Topic :: Internet :: WWW/HTTP :: Dynamic Content
Classifier: Topic :: Software Development :: Libraries :: Python Modules
Requires-Dist: colorama
Requires-Dist: fire
Requires-Dist: qiniu
Requires-Dist: termcolor
